tritonium_api_client/__init__.py
tritonium_api_client/api/__init__.py
tritonium_api_client/api/alerts/__init__.py
tritonium_api_client/api/alerts/get_alert.py
tritonium_api_client/api/alerts/get_alerts.py
tritonium_api_client/api/alerts/patch_alert.py
tritonium_api_client/api/alerts/post_alert_assign.py
tritonium_api_client/api/api_keys/__init__.py
tritonium_api_client/api/api_keys/create_api_key.py
tritonium_api_client/api/api_keys/delete_api_key.py
tritonium_api_client/api/api_keys/get_api_key.py
tritonium_api_client/api/api_keys/list_api_key_scopes.py
tritonium_api_client/api/api_keys/list_api_keys.py
tritonium_api_client/api/api_keys/rotate_api_key.py
tritonium_api_client/api/api_keys/update_api_key.py
tritonium_api_client/api/apps/__init__.py
tritonium_api_client/api/apps/delete_competitor.py
tritonium_api_client/api/apps/get_apps.py
tritonium_api_client/api/apps/get_competitors.py
tritonium_api_client/api/apps/get_feature_history.py
tritonium_api_client/api/apps/patch_app_auto_sync.py
tritonium_api_client/api/apps/post_app_auto_sync.py
tritonium_api_client/api/apps/post_apps_analyze.py
tritonium_api_client/api/apps/post_apps_connect.py
tritonium_api_client/api/apps/post_apps_connect_alias.py
tritonium_api_client/api/apps/post_apps_sync.py
tritonium_api_client/api/apps/post_competitor.py
tritonium_api_client/api/auth/__init__.py
tritonium_api_client/api/auth/post_forgot_password.py
tritonium_api_client/api/auth/post_google_sso.py
tritonium_api_client/api/auth/post_login.py
tritonium_api_client/api/auth/post_microsoft_sso.py
tritonium_api_client/api/auth/post_register.py
tritonium_api_client/api/auth/post_resend_verification.py
tritonium_api_client/api/auth/post_reset_password.py
tritonium_api_client/api/auth/post_verify_email.py
tritonium_api_client/api/billing/__init__.py
tritonium_api_client/api/billing/get_bill_forecast.py
tritonium_api_client/api/billing/get_detect_country.py
tritonium_api_client/api/billing/get_invoices.py
tritonium_api_client-2.1.1.dist-info/METADATA
tritonium_api_client-2.1.1.dist-info/WHEEL
tritonium_api_client-2.1.1.dist-info/RECORD
