Metadata-Version: 2.4
Name: tritonium-api-client
Version: 2.1.1
Summary: Official Python SDK for the Tritonium API - Customer feedback analytics platform
License: MIT
Keywords: tritonium,api,sdk,reviews,analytics,feedback
Author: Tritonium
Author-email: support@tritonium.com
Requires-Python: >=3.9,<4.0
Classifier: Development Status :: 5 - Production/Stable
Classifier: Intended Audience :: Developers
Classifier: License :: OSI Approved :: MIT License
Classifier: Operating System :: OS Independent
Classifier: Programming Language :: Python :: 3
Classifier: Programming Language :: Python :: 3.9
Classifier: Programming Language :: Python :: 3.10
Classifier: Programming Language :: Python :: 3.11
Classifier: Programming Language :: Python :: 3.12
Classifier: Programming Language :: Python :: 3.13
Classifier: Programming Language :: Python :: 3.14
Classifier: Topic :: Software Development :: Libraries :: Python Modules
Classifier: Typing :: Typed
Requires-Dist: attrs (>=22.2.0)
Requires-Dist: httpx (>=0.23.0,<0.29.0)
Requires-Dist: python-dateutil (>=2.8.0,<3.0.0)
Project-URL: Documentation, https://api.tritonium.com/api/v1/docs
Project-URL: Homepage, https://tritonium.com
Project-URL: Repository, https://github.com/tritonium/python-sdk
